{
  "header": {
    "menu": [
      {
        "link": "hero",
        "title": "Home",
        "isDropdown": false
      },
      {
        "link": "benefits",
        "title": "Benefits",
        "isDropdown": false
      },
      {
        "link": "pricing",
        "title": "Pricing",
        "isDropdown": false
      },
      {
        "link": "author",
        "title": "Author",
        "isDropdown": false
      },
      {
        "link": "justus",
        "title": "JustUS",
        "isDropdown": false
      },
      {
        "link": "contact",
        "title": "Contact",
        "isDropdown": false
      }
    ]
  }
}
